monocr/__init__.py
monocr/cli.py
monocr/config.py
monocr/download.py
monocr/exceptions.py
monocr/model.py
monocr/ocr.py
monocr/segmenter.py
monocr/assets/valid_chars.txt
monocr-0.1.18.dist-info/licenses/LICENSE
monocr-0.1.18.dist-info/METADATA
monocr-0.1.18.dist-info/WHEEL
monocr-0.1.18.dist-info/entry_points.txt
monocr-0.1.18.dist-info/top_level.txt
monocr-0.1.18.dist-info/RECORD
