Metadata-Version: 2.4
Name: monocr
Version: 0.1.18
Summary: Optical Character Recognition for Mon text
Author-email: janakhpon <jnovaxer@gmail.com>
License-Expression: MIT
Project-URL: Repository, https://github.com/janakhpon/monocr
Keywords: mon,ocr,text-recognition
Classifier: Development Status :: 4 - Beta
Classifier: Intended Audience :: Developers
Classifier: Intended Audience :: Science/Research
Classifier: Operating System :: OS Independent
Classifier: Programming Language :: Python :: 3
Classifier: Programming Language :: Python :: 3.11
Classifier: Programming Language :: Python :: 3.12
Classifier: Topic :: Scientific/Engineering :: Artificial Intelligence
Classifier: Topic :: Scientific/Engineering :: Image Recognition
Classifier: Topic :: Text Processing :: Linguistic
Classifier: Topic :: Software Development :: Libraries :: Python Modules
Requires-Python: >=3.11
License-File: LICENSE
Requires-Dist: torch>=2.0.0
Requires-Dist: torchvision>=0.15.0
Requires-Dist: pillow>=9.0.0
Requires-Dist: numpy>=1.21.0
Requires-Dist: click>=8.0.0
Requires-Dist: opencv-python>=4.0.0
Requires-Dist: huggingface_hub>=0.16.0
Provides-Extra: examples
Requires-Dist: pdf2image; extra == "examples"
Provides-Extra: test
Requires-Dist: pytest; extra == "test"
Dynamic: license-file
